nf_jira/__init__.py
nf_jira/wrapper_nf_jira.py
nf_jira/entities/anexo.py
nf_jira/entities/chave_acesso.py
nf_jira/entities/constants.py
nf_jira/entities/dados_basicos_fatura.py
nf_jira/entities/dados_basicos_miro.py
nf_jira/entities/detalhe.py
nf_jira/entities/fatura.py
nf_jira/entities/fatura_servico.py
nf_jira/entities/imposto_miro.py
nf_jira/entities/item.py
nf_jira/entities/item_servico.py
nf_jira/entities/itens_fatura.py
nf_jira/entities/jira_info.py
nf_jira/entities/miro.py
nf_jira/entities/nfe_sefaz.py
nf_jira/entities/nota_pedido.py
nf_jira/entities/nota_servico.py
nf_jira/entities/pagamento.py
nf_jira/entities/referencia_pedido.py
nf_jira/entities/sintese_itens.py
nf_jira/entities/sintese_servico.py
nf_jira/entities/classes/factories.py
nf_jira/entities/classes/form_jira.py
nf_jira/entities/classes/helper.py
nf_jira/entities/classes/issue_fields.py
nf_jira/entities/classes/issue_jira.py
nf_jira/entities/classes/n8n_domain.py
hnt_nf_jira_servicos_library-0.0.28.dist-info/METADATA
hnt_nf_jira_servicos_library-0.0.28.dist-info/WHEEL
hnt_nf_jira_servicos_library-0.0.28.dist-info/top_level.txt
hnt_nf_jira_servicos_library-0.0.28.dist-info/RECORD
