Metadata-Version: 2.1
Name: hnt_nf_jira_servicos_library
Version: 0.0.28
Summary: Lib to access nf from Jira
Author: Guillerme Rezende Manhaes
Maintainer: Pepe
License: MIT License
Keywords: nota_fiscal
Requires-Dist: requests
Requires-Dist: pydantic >=2.5.2
